pydijkstra/__init__.py
pydijkstra/dijkstra.py
pydijkstra-1.0.0.dist-info/LICENSE
pydijkstra-1.0.0.dist-info/METADATA
pydijkstra-1.0.0.dist-info/WHEEL
pydijkstra-1.0.0.dist-info/top_level.txt
pydijkstra-1.0.0.dist-info/RECORD
