Metadata-Version: 2.1
Name: pydijkstra
Version: 1.0.0
Summary: Package for easily applicable Dijkstra Algorithm.
Author-email: Niklas Markert <niklas.markert@outlook.de>
License: MIT License        
Project-URL: Homepage, https://github.com/nmarkert/python-dijkstra
Keywords: dijkstra,graph,pathfinding
Classifier: License :: OSI Approved :: MIT License
Classifier: Programming Language :: Python
Classifier: Programming Language :: Python :: 3
Requires-Python: >=3.9
License-File: LICENSE
